<annotation>
	<folder>Snack</folder>
	<filename>Snack50.jpg</filename>
	<path>G:\.shortcut-targets-by-id\18mHC6EH4uyesRVxj_2L-qvsVwLds8pxs\CE_Project\Dataset\General\Snack\Snack50.jpg</path>
	<source>
		<database>Unknown</database>
	</source>
	<size>
		<width>427</width>
		<height>571</height>
		<depth>3</depth>
	</size>
	<segmented>0</segmented>
	<object>
		<name>Snack</name>
		<pose>Unspecified</pose>
		<truncated>0</truncated>
		<difficult>0</difficult>
		<bndbox>
			<xmin>69</xmin>
			<ymin>30</ymin>
			<xmax>378</xmax>
			<ymax>544</ymax>
		</bndbox>
	</object>
</annotation>
