<annotation>
	<folder>XML</folder>
	<filename>Aerosol_cans21_aug0.jpg</filename>
	<path>D:\Downloads\Compressed\224\k\Aerosol_cans21_aug0.jpg</path>
	<source>
		<database>Unknown</database>
	</source>
	<size>
		<width>224</width>
		<height>224</height>
		<depth>3</depth>
	</size>
	<segmented>0</segmented>
	<object>
		<name>aerosol_cans</name>
		<pose>Unspecified</pose>
		<truncated>0</truncated>
		<difficult>0</difficult>
		<bndbox>
			<xmin>36</xmin>
			<ymin>73</ymin>
			<xmax>123</xmax>
			<ymax>134</ymax>
		</bndbox>
	</object>
	<object>
		<name>aerosol_cans</name>
		<pose>Unspecified</pose>
		<truncated>0</truncated>
		<difficult>0</difficult>
		<bndbox>
			<xmin>112</xmin>
			<ymin>7</ymin>
			<xmax>162</xmax>
			<ymax>74</ymax>
		</bndbox>
	</object>
	<object>
		<name>aerosol_cans</name>
		<pose>Unspecified</pose>
		<truncated>0</truncated>
		<difficult>0</difficult>
		<bndbox>
			<xmin>32</xmin>
			<ymin>0</ymin>
			<xmax>85</xmax>
			<ymax>52</ymax>
		</bndbox>
	</object>
	<object>
		<name>aerosol_cans</name>
		<pose>Unspecified</pose>
		<truncated>0</truncated>
		<difficult>0</difficult>
		<bndbox>
			<xmin>0</xmin>
			<ymin>36</ymin>
			<xmax>51</xmax>
			<ymax>91</ymax>
		</bndbox>
	</object>
	<object>
		<name>aerosol_cans</name>
		<pose>Unspecified</pose>
		<truncated>0</truncated>
		<difficult>0</difficult>
		<bndbox>
			<xmin>0</xmin>
			<ymin>90</ymin>
			<xmax>57</xmax>
			<ymax>155</ymax>
		</bndbox>
	</object>
	<object>
		<name>aerosol_cans</name>
		<pose>Unspecified</pose>
		<truncated>0</truncated>
		<difficult>0</difficult>
		<bndbox>
			<xmin>159</xmin>
			<ymin>78</ymin>
			<xmax>223</xmax>
			<ymax>137</ymax>
		</bndbox>
	</object>
	<object>
		<name>aerosol_cans</name>
		<pose>Unspecified</pose>
		<truncated>0</truncated>
		<difficult>0</difficult>
		<bndbox>
			<xmin>163</xmin>
			<ymin>51</ymin>
			<xmax>208</xmax>
			<ymax>110</ymax>
		</bndbox>
	</object>
	<object>
		<name>aerosol_cans</name>
		<pose>Unspecified</pose>
		<truncated>0</truncated>
		<difficult>0</difficult>
		<bndbox>
			<xmin>43</xmin>
			<ymin>38</ymin>
			<xmax>97</xmax>
			<ymax>92</ymax>
		</bndbox>
	</object>
	<object>
		<name>aerosol_cans</name>
		<pose>Unspecified</pose>
		<truncated>0</truncated>
		<difficult>0</difficult>
		<bndbox>
			<xmin>0</xmin>
			<ymin>0</ymin>
			<xmax>40</xmax>
			<ymax>47</ymax>
		</bndbox>
	</object>
</annotation>
