<annotation>
	<folder>XML</folder>
	<filename>Battery269.jpg</filename>
	<path>D:\Downloads\Compressed\224\k\Battery269.jpg</path>
	<source>
		<database>Unknown</database>
	</source>
	<size>
		<width>224</width>
		<height>224</height>
		<depth>3</depth>
	</size>
	<segmented>0</segmented>
	<object>
		<name>battery</name>
		<pose>Unspecified</pose>
		<truncated>0</truncated>
		<difficult>0</difficult>
		<bndbox>
			<xmin>70</xmin>
			<ymin>118</ymin>
			<xmax>192</xmax>
			<ymax>200</ymax>
		</bndbox>
	</object>
	<object>
		<name>battery</name>
		<pose>Unspecified</pose>
		<truncated>0</truncated>
		<difficult>0</difficult>
		<bndbox>
			<xmin>49</xmin>
			<ymin>107</ymin>
			<xmax>168</xmax>
			<ymax>185</ymax>
		</bndbox>
	</object>
	<object>
		<name>battery</name>
		<pose>Unspecified</pose>
		<truncated>0</truncated>
		<difficult>0</difficult>
		<bndbox>
			<xmin>80</xmin>
			<ymin>22</ymin>
			<xmax>118</xmax>
			<ymax>143</ymax>
		</bndbox>
	</object>
	<object>
		<name>battery</name>
		<pose>Unspecified</pose>
		<truncated>0</truncated>
		<difficult>0</difficult>
		<bndbox>
			<xmin>48</xmin>
			<ymin>30</ymin>
			<xmax>89</xmax>
			<ymax>158</ymax>
		</bndbox>
	</object>
</annotation>
