<annotation>
	<folder>XML</folder>
	<filename>carton59_aug0.jpg</filename>
	<path>D:\Downloads\Compressed\224\k\carton59_aug0.jpg</path>
	<source>
		<database>Unknown</database>
	</source>
	<size>
		<width>224</width>
		<height>224</height>
		<depth>3</depth>
	</size>
	<segmented>0</segmented>
	<object>
		<name>carton</name>
		<pose>Unspecified</pose>
		<truncated>0</truncated>
		<difficult>0</difficult>
		<bndbox>
			<xmin>161</xmin>
			<ymin>22</ymin>
			<xmax>193</xmax>
			<ymax>62</ymax>
		</bndbox>
	</object>
	<object>
		<name>carton</name>
		<pose>Unspecified</pose>
		<truncated>0</truncated>
		<difficult>0</difficult>
		<bndbox>
			<xmin>130</xmin>
			<ymin>24</ymin>
			<xmax>162</xmax>
			<ymax>67</ymax>
		</bndbox>
	</object>
	<object>
		<name>carton</name>
		<pose>Unspecified</pose>
		<truncated>0</truncated>
		<difficult>0</difficult>
		<bndbox>
			<xmin>122</xmin>
			<ymin>16</ymin>
			<xmax>153</xmax>
			<ymax>58</ymax>
		</bndbox>
	</object>
	<object>
		<name>carton</name>
		<pose>Unspecified</pose>
		<truncated>0</truncated>
		<difficult>0</difficult>
		<bndbox>
			<xmin>76</xmin>
			<ymin>12</ymin>
			<xmax>116</xmax>
			<ymax>74</ymax>
		</bndbox>
	</object>
	<object>
		<name>carton</name>
		<pose>Unspecified</pose>
		<truncated>0</truncated>
		<difficult>0</difficult>
		<bndbox>
			<xmin>9</xmin>
			<ymin>32</ymin>
			<xmax>68</xmax>
			<ymax>140</ymax>
		</bndbox>
	</object>
	<object>
		<name>carton</name>
		<pose>Unspecified</pose>
		<truncated>0</truncated>
		<difficult>0</difficult>
		<bndbox>
			<xmin>74</xmin>
			<ymin>73</ymin>
			<xmax>131</xmax>
			<ymax>160</ymax>
		</bndbox>
	</object>
	<object>
		<name>carton</name>
		<pose>Unspecified</pose>
		<truncated>0</truncated>
		<difficult>0</difficult>
		<bndbox>
			<xmin>151</xmin>
			<ymin>79</ymin>
			<xmax>190</xmax>
			<ymax>154</ymax>
		</bndbox>
	</object>
</annotation>
