<annotation>
	<folder>XML</folder>
	<filename>Correction_fluid69_aug1.jpg</filename>
	<path>D:\Downloads\Compressed\224\k\Correction_fluid69_aug1.jpg</path>
	<source>
		<database>Unknown</database>
	</source>
	<size>
		<width>224</width>
		<height>224</height>
		<depth>3</depth>
	</size>
	<segmented>0</segmented>
	<object>
		<name>correction_fluid</name>
		<pose>Unspecified</pose>
		<truncated>0</truncated>
		<difficult>0</difficult>
		<bndbox>
			<xmin>43</xmin>
			<ymin>19</ymin>
			<xmax>206</xmax>
			<ymax>147</ymax>
		</bndbox>
	</object>
	<object>
		<name>correction_fluid</name>
		<pose>Unspecified</pose>
		<truncated>0</truncated>
		<difficult>0</difficult>
		<bndbox>
			<xmin>5</xmin>
			<ymin>67</ymin>
			<xmax>201</xmax>
			<ymax>219</ymax>
		</bndbox>
	</object>
</annotation>
