<annotation>
	<folder>XML</folder>
	<filename>Foam_box72.jpg</filename>
	<path>D:\Downloads\Compressed\224\k\Foam_box72.jpg</path>
	<source>
		<database>Unknown</database>
	</source>
	<size>
		<width>224</width>
		<height>224</height>
		<depth>3</depth>
	</size>
	<segmented>0</segmented>
	<object>
		<name>foam_box</name>
		<pose>Unspecified</pose>
		<truncated>0</truncated>
		<difficult>0</difficult>
		<bndbox>
			<xmin>101</xmin>
			<ymin>23</ymin>
			<xmax>218</xmax>
			<ymax>116</ymax>
		</bndbox>
	</object>
	<object>
		<name>foam_box</name>
		<pose>Unspecified</pose>
		<truncated>0</truncated>
		<difficult>0</difficult>
		<bndbox>
			<xmin>6</xmin>
			<ymin>17</ymin>
			<xmax>104</xmax>
			<ymax>93</ymax>
		</bndbox>
	</object>
</annotation>
