<annotation>
	<folder>XML</folder>
	<filename>Light_bulb161_aug0.jpg</filename>
	<path>D:\Downloads\Compressed\224\k\Light_bulb161_aug0.jpg</path>
	<source>
		<database>Unknown</database>
	</source>
	<size>
		<width>224</width>
		<height>224</height>
		<depth>3</depth>
	</size>
	<segmented>0</segmented>
	<object>
		<name>light_bulb</name>
		<pose>Unspecified</pose>
		<truncated>0</truncated>
		<difficult>0</difficult>
		<bndbox>
			<xmin>0</xmin>
			<ymin>76</ymin>
			<xmax>68</xmax>
			<ymax>145</ymax>
		</bndbox>
	</object>
	<object>
		<name>light_bulb</name>
		<pose>Unspecified</pose>
		<truncated>0</truncated>
		<difficult>0</difficult>
		<bndbox>
			<xmin>50</xmin>
			<ymin>76</ymin>
			<xmax>88</xmax>
			<ymax>115</ymax>
		</bndbox>
	</object>
	<object>
		<name>light_bulb</name>
		<pose>Unspecified</pose>
		<truncated>0</truncated>
		<difficult>0</difficult>
		<bndbox>
			<xmin>34</xmin>
			<ymin>71</ymin>
			<xmax>70</xmax>
			<ymax>108</ymax>
		</bndbox>
	</object>
	<object>
		<name>light_bulb</name>
		<pose>Unspecified</pose>
		<truncated>0</truncated>
		<difficult>0</difficult>
		<bndbox>
			<xmin>33</xmin>
			<ymin>6</ymin>
			<xmax>65</xmax>
			<ymax>79</ymax>
		</bndbox>
	</object>
	<object>
		<name>light_bulb</name>
		<pose>Unspecified</pose>
		<truncated>0</truncated>
		<difficult>0</difficult>
		<bndbox>
			<xmin>20</xmin>
			<ymin>50</ymin>
			<xmax>54</xmax>
			<ymax>85</ymax>
		</bndbox>
	</object>
	<object>
		<name>light_bulb</name>
		<pose>Unspecified</pose>
		<truncated>0</truncated>
		<difficult>0</difficult>
		<bndbox>
			<xmin>50</xmin>
			<ymin>31</ymin>
			<xmax>90</xmax>
			<ymax>74</ymax>
		</bndbox>
	</object>
	<object>
		<name>light_bulb</name>
		<pose>Unspecified</pose>
		<truncated>0</truncated>
		<difficult>0</difficult>
		<bndbox>
			<xmin>7</xmin>
			<ymin>114</ymin>
			<xmax>85</xmax>
			<ymax>165</ymax>
		</bndbox>
	</object>
	<object>
		<name>light_bulb</name>
		<pose>Unspecified</pose>
		<truncated>0</truncated>
		<difficult>0</difficult>
		<bndbox>
			<xmin>71</xmin>
			<ymin>111</ymin>
			<xmax>109</xmax>
			<ymax>158</ymax>
		</bndbox>
	</object>
	<object>
		<name>light_bulb</name>
		<pose>Unspecified</pose>
		<truncated>0</truncated>
		<difficult>0</difficult>
		<bndbox>
			<xmin>87</xmin>
			<ymin>93</ymin>
			<xmax>121</xmax>
			<ymax>149</ymax>
		</bndbox>
	</object>
	<object>
		<name>light_bulb</name>
		<pose>Unspecified</pose>
		<truncated>0</truncated>
		<difficult>0</difficult>
		<bndbox>
			<xmin>79</xmin>
			<ymin>65</ymin>
			<xmax>111</xmax>
			<ymax>91</ymax>
		</bndbox>
	</object>
	<object>
		<name>light_bulb</name>
		<pose>Unspecified</pose>
		<truncated>0</truncated>
		<difficult>0</difficult>
		<bndbox>
			<xmin>80</xmin>
			<ymin>28</ymin>
			<xmax>114</xmax>
			<ymax>72</ymax>
		</bndbox>
	</object>
	<object>
		<name>light_bulb</name>
		<pose>Unspecified</pose>
		<truncated>0</truncated>
		<difficult>0</difficult>
		<bndbox>
			<xmin>98</xmin>
			<ymin>19</ymin>
			<xmax>127</xmax>
			<ymax>41</ymax>
		</bndbox>
	</object>
	<object>
		<name>light_bulb</name>
		<pose>Unspecified</pose>
		<truncated>0</truncated>
		<difficult>0</difficult>
		<bndbox>
			<xmin>86</xmin>
			<ymin>11</ymin>
			<xmax>111</xmax>
			<ymax>46</ymax>
		</bndbox>
	</object>
	<object>
		<name>light_bulb</name>
		<pose>Unspecified</pose>
		<truncated>0</truncated>
		<difficult>0</difficult>
		<bndbox>
			<xmin>58</xmin>
			<ymin>16</ymin>
			<xmax>88</xmax>
			<ymax>50</ymax>
		</bndbox>
	</object>
	<object>
		<name>light_bulb</name>
		<pose>Unspecified</pose>
		<truncated>0</truncated>
		<difficult>0</difficult>
		<bndbox>
			<xmin>124</xmin>
			<ymin>13</ymin>
			<xmax>162</xmax>
			<ymax>46</ymax>
		</bndbox>
	</object>
	<object>
		<name>light_bulb</name>
		<pose>Unspecified</pose>
		<truncated>0</truncated>
		<difficult>0</difficult>
		<bndbox>
			<xmin>140</xmin>
			<ymin>22</ymin>
			<xmax>182</xmax>
			<ymax>67</ymax>
		</bndbox>
	</object>
	<object>
		<name>light_bulb</name>
		<pose>Unspecified</pose>
		<truncated>0</truncated>
		<difficult>0</difficult>
		<bndbox>
			<xmin>111</xmin>
			<ymin>77</ymin>
			<xmax>145</xmax>
			<ymax>113</ymax>
		</bndbox>
	</object>
	<object>
		<name>light_bulb</name>
		<pose>Unspecified</pose>
		<truncated>0</truncated>
		<difficult>0</difficult>
		<bndbox>
			<xmin>103</xmin>
			<ymin>43</ymin>
			<xmax>149</xmax>
			<ymax>95</ymax>
		</bndbox>
	</object>
	<object>
		<name>light_bulb</name>
		<pose>Unspecified</pose>
		<truncated>0</truncated>
		<difficult>0</difficult>
		<bndbox>
			<xmin>149</xmin>
			<ymin>78</ymin>
			<xmax>179</xmax>
			<ymax>135</ymax>
		</bndbox>
	</object>
	<object>
		<name>light_bulb</name>
		<pose>Unspecified</pose>
		<truncated>0</truncated>
		<difficult>0</difficult>
		<bndbox>
			<xmin>111</xmin>
			<ymin>101</ymin>
			<xmax>165</xmax>
			<ymax>158</ymax>
		</bndbox>
	</object>
	<object>
		<name>light_bulb</name>
		<pose>Unspecified</pose>
		<truncated>0</truncated>
		<difficult>0</difficult>
		<bndbox>
			<xmin>117</xmin>
			<ymin>144</ymin>
			<xmax>158</xmax>
			<ymax>166</ymax>
		</bndbox>
	</object>
	<object>
		<name>light_bulb</name>
		<pose>Unspecified</pose>
		<truncated>0</truncated>
		<difficult>0</difficult>
		<bndbox>
			<xmin>150</xmin>
			<ymin>78</ymin>
			<xmax>221</xmax>
			<ymax>107</ymax>
		</bndbox>
	</object>
	<object>
		<name>light_bulb</name>
		<pose>Unspecified</pose>
		<truncated>0</truncated>
		<difficult>0</difficult>
		<bndbox>
			<xmin>198</xmin>
			<ymin>98</ymin>
			<xmax>224</xmax>
			<ymax>154</ymax>
		</bndbox>
	</object>
	<object>
		<name>light_bulb</name>
		<pose>Unspecified</pose>
		<truncated>0</truncated>
		<difficult>0</difficult>
		<bndbox>
			<xmin>162</xmin>
			<ymin>99</ymin>
			<xmax>210</xmax>
			<ymax>158</ymax>
		</bndbox>
	</object>
	<object>
		<name>light_bulb</name>
		<pose>Unspecified</pose>
		<truncated>0</truncated>
		<difficult>0</difficult>
		<bndbox>
			<xmin>150</xmin>
			<ymin>142</ymin>
			<xmax>181</xmax>
			<ymax>171</ymax>
		</bndbox>
	</object>
	<object>
		<name>light_bulb</name>
		<pose>Unspecified</pose>
		<truncated>0</truncated>
		<difficult>0</difficult>
		<bndbox>
			<xmin>153</xmin>
			<ymin>43</ymin>
			<xmax>212</xmax>
			<ymax>90</ymax>
		</bndbox>
	</object>
</annotation>
