<annotation>
	<folder>XML</folder>
	<filename>Light_bulb241_aug0.jpg</filename>
	<path>D:\Downloads\Compressed\224\k\Light_bulb241_aug0.jpg</path>
	<source>
		<database>Unknown</database>
	</source>
	<size>
		<width>224</width>
		<height>224</height>
		<depth>3</depth>
	</size>
	<segmented>0</segmented>
	<object>
		<name>light_bulb</name>
		<pose>Unspecified</pose>
		<truncated>0</truncated>
		<difficult>0</difficult>
		<bndbox>
			<xmin>29</xmin>
			<ymin>16</ymin>
			<xmax>96</xmax>
			<ymax>103</ymax>
		</bndbox>
	</object>
	<object>
		<name>light_bulb</name>
		<pose>Unspecified</pose>
		<truncated>0</truncated>
		<difficult>0</difficult>
		<bndbox>
			<xmin>104</xmin>
			<ymin>45</ymin>
			<xmax>142</xmax>
			<ymax>98</ymax>
		</bndbox>
	</object>
	<object>
		<name>light_bulb</name>
		<pose>Unspecified</pose>
		<truncated>0</truncated>
		<difficult>0</difficult>
		<bndbox>
			<xmin>149</xmin>
			<ymin>61</ymin>
			<xmax>197</xmax>
			<ymax>116</ymax>
		</bndbox>
	</object>
	<object>
		<name>light_bulb</name>
		<pose>Unspecified</pose>
		<truncated>0</truncated>
		<difficult>0</difficult>
		<bndbox>
			<xmin>192</xmin>
			<ymin>39</ymin>
			<xmax>224</xmax>
			<ymax>109</ymax>
		</bndbox>
	</object>
	<object>
		<name>light_bulb</name>
		<pose>Unspecified</pose>
		<truncated>0</truncated>
		<difficult>0</difficult>
		<bndbox>
			<xmin>0</xmin>
			<ymin>56</ymin>
			<xmax>44</xmax>
			<ymax>158</ymax>
		</bndbox>
	</object>
</annotation>
