<annotation>
	<folder>XML</folder>
	<filename>Light_bulb63_aug0.jpg</filename>
	<path>D:\Downloads\Compressed\224\k\Light_bulb63_aug0.jpg</path>
	<source>
		<database>Unknown</database>
	</source>
	<size>
		<width>224</width>
		<height>224</height>
		<depth>3</depth>
	</size>
	<segmented>0</segmented>
	<object>
		<name>light_bulb</name>
		<pose>Unspecified</pose>
		<truncated>0</truncated>
		<difficult>0</difficult>
		<bndbox>
			<xmin>0</xmin>
			<ymin>105</ymin>
			<xmax>224</xmax>
			<ymax>143</ymax>
		</bndbox>
	</object>
	<object>
		<name>light_bulb</name>
		<pose>Unspecified</pose>
		<truncated>0</truncated>
		<difficult>0</difficult>
		<bndbox>
			<xmin>0</xmin>
			<ymin>80</ymin>
			<xmax>222</xmax>
			<ymax>108</ymax>
		</bndbox>
	</object>
	<object>
		<name>light_bulb</name>
		<pose>Unspecified</pose>
		<truncated>0</truncated>
		<difficult>0</difficult>
		<bndbox>
			<xmin>6</xmin>
			<ymin>51</ymin>
			<xmax>221</xmax>
			<ymax>83</ymax>
		</bndbox>
	</object>
	<object>
		<name>light_bulb</name>
		<pose>Unspecified</pose>
		<truncated>0</truncated>
		<difficult>0</difficult>
		<bndbox>
			<xmin>5</xmin>
			<ymin>25</ymin>
			<xmax>214</xmax>
			<ymax>59</ymax>
		</bndbox>
	</object>
	<object>
		<name>light_bulb</name>
		<pose>Unspecified</pose>
		<truncated>0</truncated>
		<difficult>0</difficult>
		<bndbox>
			<xmin>10</xmin>
			<ymin>2</ymin>
			<xmax>213</xmax>
			<ymax>32</ymax>
		</bndbox>
	</object>
</annotation>
