<annotation>
	<folder>XML</folder>
	<filename>Paper_cup118.jpg</filename>
	<path>D:\Downloads\Compressed\224\k\Paper_cup118.jpg</path>
	<source>
		<database>Unknown</database>
	</source>
	<size>
		<width>224</width>
		<height>224</height>
		<depth>3</depth>
	</size>
	<segmented>0</segmented>
	<object>
		<name>paper_cup</name>
		<pose>Unspecified</pose>
		<truncated>0</truncated>
		<difficult>0</difficult>
		<bndbox>
			<xmin>40</xmin>
			<ymin>40</ymin>
			<xmax>116</xmax>
			<ymax>97</ymax>
		</bndbox>
	</object>
	<object>
		<name>paper_cup</name>
		<pose>Unspecified</pose>
		<truncated>0</truncated>
		<difficult>0</difficult>
		<bndbox>
			<xmin>0</xmin>
			<ymin>51</ymin>
			<xmax>71</xmax>
			<ymax>110</ymax>
		</bndbox>
	</object>
	<object>
		<name>paper_cup</name>
		<pose>Unspecified</pose>
		<truncated>0</truncated>
		<difficult>0</difficult>
		<bndbox>
			<xmin>141</xmin>
			<ymin>62</ymin>
			<xmax>214</xmax>
			<ymax>149</ymax>
		</bndbox>
	</object>
	<object>
		<name>paper_cup</name>
		<pose>Unspecified</pose>
		<truncated>0</truncated>
		<difficult>0</difficult>
		<bndbox>
			<xmin>81</xmin>
			<ymin>73</ymin>
			<xmax>148</xmax>
			<ymax>164</ymax>
		</bndbox>
	</object>
	<object>
		<name>paper_cup</name>
		<pose>Unspecified</pose>
		<truncated>0</truncated>
		<difficult>0</difficult>
		<bndbox>
			<xmin>44</xmin>
			<ymin>100</ymin>
			<xmax>102</xmax>
			<ymax>163</ymax>
		</bndbox>
	</object>
</annotation>
