<annotation>
	<folder>PlasticBox</folder>
	<filename>Plastic Box269.jpg</filename>
	<path>G:\.shortcut-targets-by-id\18mHC6EH4uyesRVxj_2L-qvsVwLds8pxs\CE_Project\Dataset\General\PlasticBox\Plastic Box269.jpg</path>
	<source>
		<database>Unknown</database>
	</source>
	<size>
		<width>630</width>
		<height>420</height>
		<depth>3</depth>
	</size>
	<segmented>0</segmented>
	<object>
		<name>PlasticBox</name>
		<pose>Unspecified</pose>
		<truncated>0</truncated>
		<difficult>0</difficult>
		<bndbox>
			<xmin>119</xmin>
			<ymin>122</ymin>
			<xmax>530</xmax>
			<ymax>396</ymax>
		</bndbox>
	</object>
</annotation>
