<annotation>
	<folder>Aerosol_cans</folder>
	<filename>Aerosol_cans79.jpg</filename>
	<path>G:\.shortcut-targets-by-id\18mHC6EH4uyesRVxj_2L-qvsVwLds8pxs\CE_Project\Dataset\Hazardous waste\Aerosol_cans\Aerosol_cans79.jpg</path>
	<source>
		<database>Unknown</database>
	</source>
	<size>
		<width>960</width>
		<height>640</height>
		<depth>3</depth>
	</size>
	<segmented>0</segmented>
	<object>
		<name>Aerosol_cans</name>
		<pose>Unspecified</pose>
		<truncated>0</truncated>
		<difficult>0</difficult>
		<bndbox>
			<xmin>465</xmin>
			<ymin>49</ymin>
			<xmax>646</xmax>
			<ymax>529</ymax>
		</bndbox>
	</object>
	<object>
		<name>Aerosol_cans</name>
		<pose>Unspecified</pose>
		<truncated>0</truncated>
		<difficult>0</difficult>
		<bndbox>
			<xmin>186</xmin>
			<ymin>303</ymin>
			<xmax>533</xmax>
			<ymax>493</ymax>
		</bndbox>
	</object>
</annotation>
