<annotation>
	<folder>Battery</folder>
	<filename>Battery426.jpg</filename>
	<path>D:\project\Waste-Sorting-Machine-by-Machine-Learning-System\Dataset\Hazardous waste\Battery\Battery426.jpg</path>
	<source>
		<database>Unknown</database>
	</source>
	<size>
		<width>1000</width>
		<height>1000</height>
		<depth>3</depth>
	</size>
	<segmented>0</segmented>
	<object>
		<name>Battery</name>
		<pose>Unspecified</pose>
		<truncated>0</truncated>
		<difficult>0</difficult>
		<bndbox>
			<xmin>449</xmin>
			<ymin>432</ymin>
			<xmax>521</xmax>
			<ymax>667</ymax>
		</bndbox>
	</object>
	<object>
		<name>Battery</name>
		<pose>Unspecified</pose>
		<truncated>0</truncated>
		<difficult>0</difficult>
		<bndbox>
			<xmin>383</xmin>
			<ymin>426</ymin>
			<xmax>453</xmax>
			<ymax>655</ymax>
		</bndbox>
	</object>
</annotation>
