<annotation>
	<folder>Battery</folder>
	<filename>Battery93.jpg</filename>
	<path>D:\project\Waste-Sorting-Machine-by-Machine-Learning-System\Dataset\Hazardous waste\Battery\Battery93.jpg</path>
	<source>
		<database>Unknown</database>
	</source>
	<size>
		<width>400</width>
		<height>193</height>
		<depth>3</depth>
	</size>
	<segmented>0</segmented>
	<object>
		<name>Battery</name>
		<pose>Unspecified</pose>
		<truncated>0</truncated>
		<difficult>0</difficult>
		<bndbox>
			<xmin>247</xmin>
			<ymin>5</ymin>
			<xmax>285</xmax>
			<ymax>64</ymax>
		</bndbox>
	</object>
	<object>
		<name>Battery</name>
		<pose>Unspecified</pose>
		<truncated>0</truncated>
		<difficult>0</difficult>
		<bndbox>
			<xmin>212</xmin>
			<ymin>5</ymin>
			<xmax>245</xmax>
			<ymax>62</ymax>
		</bndbox>
	</object>
	<object>
		<name>Battery</name>
		<pose>Unspecified</pose>
		<truncated>0</truncated>
		<difficult>0</difficult>
		<bndbox>
			<xmin>252</xmin>
			<ymin>70</ymin>
			<xmax>287</xmax>
			<ymax>128</ymax>
		</bndbox>
	</object>
	<object>
		<name>Battery</name>
		<pose>Unspecified</pose>
		<truncated>0</truncated>
		<difficult>0</difficult>
		<bndbox>
			<xmin>213</xmin>
			<ymin>71</ymin>
			<xmax>248</xmax>
			<ymax>130</ymax>
		</bndbox>
	</object>
</annotation>
