<annotation>
	<folder>Cleaning_solution</folder>
	<filename>Cleaning_solution320.jpg</filename>
	<path>D:\project\Waste-Sorting-Machine-by-Machine-Learning-System\Dataset\Hazardous waste\Cleaning_solution\Cleaning_solution320.jpg</path>
	<source>
		<database>Unknown</database>
	</source>
	<size>
		<width>3024</width>
		<height>3024</height>
		<depth>3</depth>
	</size>
	<segmented>0</segmented>
	<object>
		<name>Cleaning_solution</name>
		<pose>Unspecified</pose>
		<truncated>0</truncated>
		<difficult>0</difficult>
		<bndbox>
			<xmin>336</xmin>
			<ymin>17</ymin>
			<xmax>2643</xmax>
			<ymax>2982</ymax>
		</bndbox>
	</object>
</annotation>
