<annotation>
	<folder>Insecticide</folder>
	<filename>Insecticide53.jpg</filename>
	<path>D:\project\Hazardous waste\Insecticide\Insecticide53.jpg</path>
	<source>
		<database>Unknown</database>
	</source>
	<size>
		<width>340</width>
		<height>340</height>
		<depth>3</depth>
	</size>
	<segmented>0</segmented>
	<object>
		<name>Insecticide</name>
		<pose>Unspecified</pose>
		<truncated>0</truncated>
		<difficult>0</difficult>
		<bndbox>
			<xmin>136</xmin>
			<ymin>76</ymin>
			<xmax>234</xmax>
			<ymax>336</ymax>
		</bndbox>
	</object>
</annotation>
