<annotation>
	<folder>Light_bulb</folder>
	<filename>Light_bulb71.jpg</filename>
	<path>D:\project\Hazardous waste\Light_bulb\Light_bulb71.jpg</path>
	<source>
		<database>Unknown</database>
	</source>
	<size>
		<width>671</width>
		<height>336</height>
		<depth>3</depth>
	</size>
	<segmented>0</segmented>
	<object>
		<name>Light_bulb</name>
		<pose>Unspecified</pose>
		<truncated>0</truncated>
		<difficult>0</difficult>
		<bndbox>
			<xmin>96</xmin>
			<ymin>172</ymin>
			<xmax>186</xmax>
			<ymax>272</ymax>
		</bndbox>
	</object>
	<object>
		<name>Light_bulb</name>
		<pose>Unspecified</pose>
		<truncated>0</truncated>
		<difficult>0</difficult>
		<bndbox>
			<xmin>261</xmin>
			<ymin>195</ymin>
			<xmax>343</xmax>
			<ymax>288</ymax>
		</bndbox>
	</object>
	<object>
		<name>Light_bulb</name>
		<pose>Unspecified</pose>
		<truncated>0</truncated>
		<difficult>0</difficult>
		<bndbox>
			<xmin>340</xmin>
			<ymin>194</ymin>
			<xmax>422</xmax>
			<ymax>287</ymax>
		</bndbox>
	</object>
	<object>
		<name>Light_bulb</name>
		<pose>Unspecified</pose>
		<truncated>0</truncated>
		<difficult>0</difficult>
		<bndbox>
			<xmin>418</xmin>
			<ymin>196</ymin>
			<xmax>500</xmax>
			<ymax>289</ymax>
		</bndbox>
	</object>
	<object>
		<name>Light_bulb</name>
		<pose>Unspecified</pose>
		<truncated>0</truncated>
		<difficult>0</difficult>
		<bndbox>
			<xmin>497</xmin>
			<ymin>195</ymin>
			<xmax>579</xmax>
			<ymax>288</ymax>
		</bndbox>
	</object>
	<object>
		<name>Light_bulb</name>
		<pose>Unspecified</pose>
		<truncated>0</truncated>
		<difficult>0</difficult>
		<bndbox>
			<xmin>577</xmin>
			<ymin>196</ymin>
			<xmax>659</xmax>
			<ymax>289</ymax>
		</bndbox>
	</object>
</annotation>
