<annotation>
	<folder>Light_bulb</folder>
	<filename>Light_bulb367.jpg</filename>
	<path>D:\project\Hazardous waste\Light_bulb\Light_bulb367.jpg</path>
	<source>
		<database>Unknown</database>
	</source>
	<size>
		<width>640</width>
		<height>640</height>
		<depth>3</depth>
	</size>
	<segmented>0</segmented>
	<object>
		<name>Light_bulb</name>
		<pose>Unspecified</pose>
		<truncated>0</truncated>
		<difficult>0</difficult>
		<bndbox>
			<xmin>182</xmin>
			<ymin>17</ymin>
			<xmax>465</xmax>
			<ymax>627</ymax>
		</bndbox>
	</object>
</annotation>
