<annotation>
	<folder>Three_eye_plug</folder>
	<filename>Three_eye_plug146.jpg</filename>
	<path>D:\project\Hazardous waste\Three_eye_plug\Three_eye_plug146.jpg</path>
	<source>
		<database>Unknown</database>
	</source>
	<size>
		<width>850</width>
		<height>741</height>
		<depth>3</depth>
	</size>
	<segmented>0</segmented>
	<object>
		<name>Three_eye_plug</name>
		<pose>Unspecified</pose>
		<truncated>0</truncated>
		<difficult>0</difficult>
		<bndbox>
			<xmin>29</xmin>
			<ymin>221</ymin>
			<xmax>795</xmax>
			<ymax>736</ymax>
		</bndbox>
	</object>
</annotation>
