<annotation>
	<folder>glass_bottle</folder>
	<filename>glass_bottle87.jpg</filename>
	<path>G:\My Drive\CE_Project\Dataset\Recycle\glass_bottle\glass_bottle87.jpg</path>
	<source>
		<database>Unknown</database>
	</source>
	<size>
		<width>393</width>
		<height>250</height>
		<depth>3</depth>
	</size>
	<segmented>0</segmented>
	<object>
		<name>glass_bottle</name>
		<pose>Unspecified</pose>
		<truncated>0</truncated>
		<difficult>0</difficult>
		<bndbox>
			<xmin>32</xmin>
			<ymin>72</ymin>
			<xmax>130</xmax>
			<ymax>222</ymax>
		</bndbox>
	</object>
	<object>
		<name>glass_bottle</name>
		<pose>Unspecified</pose>
		<truncated>0</truncated>
		<difficult>0</difficult>
		<bndbox>
			<xmin>145</xmin>
			<ymin>63</ymin>
			<xmax>250</xmax>
			<ymax>227</ymax>
		</bndbox>
	</object>
	<object>
		<name>glass_bottle</name>
		<pose>Unspecified</pose>
		<truncated>0</truncated>
		<difficult>0</difficult>
		<bndbox>
			<xmin>266</xmin>
			<ymin>65</ymin>
			<xmax>375</xmax>
			<ymax>224</ymax>
		</bndbox>
	</object>
</annotation>
