<annotation>
	<folder>news_paper</folder>
	<filename>news_paper55.jpg</filename>
	<path>G:\.shortcut-targets-by-id\1QjkP-g9WnzCs2AXko23CfxIBr_eyZm1o\Recycle\news_paper\news_paper55.jpg</path>
	<source>
		<database>Unknown</database>
	</source>
	<size>
		<width>417</width>
		<height>288</height>
		<depth>3</depth>
	</size>
	<segmented>0</segmented>
	<object>
		<name>news_paper</name>
		<pose>Unspecified</pose>
		<truncated>0</truncated>
		<difficult>0</difficult>
		<bndbox>
			<xmin>28</xmin>
			<ymin>16</ymin>
			<xmax>404</xmax>
			<ymax>203</ymax>
		</bndbox>
	</object>
	<object>
		<name>news_paper</name>
		<pose>Unspecified</pose>
		<truncated>0</truncated>
		<difficult>0</difficult>
		<bndbox>
			<xmin>32</xmin>
			<ymin>72</ymin>
			<xmax>392</xmax>
			<ymax>244</ymax>
		</bndbox>
	</object>
	<object>
		<name>news_paper</name>
		<pose>Unspecified</pose>
		<truncated>0</truncated>
		<difficult>0</difficult>
		<bndbox>
			<xmin>67</xmin>
			<ymin>144</ymin>
			<xmax>395</xmax>
			<ymax>281</ymax>
		</bndbox>
	</object>
</annotation>
