<annotation>
	<folder>FoamBox</folder>
	<filename>Foam Box0.jpg</filename>
	<path>G:\.shortcut-targets-by-id\18mHC6EH4uyesRVxj_2L-qvsVwLds8pxs\CE_Project\Dataset\General\FoamBox\Foam Box0.jpg</path>
	<source>
		<database>Unknown</database>
	</source>
	<size>
		<width>223</width>
		<height>226</height>
		<depth>3</depth>
	</size>
	<segmented>0</segmented>
	<object>
		<name>FoamBox</name>
		<pose>Unspecified</pose>
		<truncated>1</truncated>
		<difficult>0</difficult>
		<bndbox>
			<xmin>1</xmin>
			<ymin>21</ymin>
			<xmax>223</xmax>
			<ymax>205</ymax>
		</bndbox>
	</object>
</annotation>
